palebluedot/apt.py
palebluedot/cli.py
palebluedot/georef.py
palebluedot/xcorr.py
palebluedot-0.1.0.dist-info/METADATA
palebluedot-0.1.0.dist-info/WHEEL
palebluedot-0.1.0.dist-info/entry_points.txt
palebluedot-0.1.0.dist-info/licenses/LICENSE
palebluedot-0.1.0.dist-info/RECORD
